mirdan/__init__.py
mirdan/config.py
mirdan/models.py
mirdan/server.py
mirdan/core/__init__.py
mirdan/core/client_registry.py
mirdan/core/code_validator.py
mirdan/core/context_aggregator.py
mirdan/core/entity_extractor.py
mirdan/core/intent_analyzer.py
mirdan/core/language_detector.py
mirdan/core/orchestrator.py
mirdan/core/pattern_matcher.py
mirdan/core/plan_validator.py
mirdan/core/prompt_composer.py
mirdan/core/quality_standards.py
mirdan/core/gatherers/__init__.py
mirdan/core/gatherers/base.py
mirdan/core/gatherers/context7.py
mirdan/core/gatherers/enyal.py
mirdan/core/gatherers/filesystem.py
mirdan/core/gatherers/github.py
mirdan/standards/__init__.py
mirdan/standards/architecture.yaml
mirdan/standards/knowledge_graphs.yaml
mirdan/standards/planning.yaml
mirdan/standards/rag_pipelines.yaml
mirdan/standards/security.yaml
mirdan/standards/frameworks/chromadb.yaml
mirdan/standards/frameworks/django.yaml
mirdan/standards/frameworks/echo.yaml
mirdan/standards/frameworks/express.yaml
mirdan/standards/frameworks/faiss.yaml
mirdan/standards/frameworks/fastapi.yaml
mirdan/standards/frameworks/gin.yaml
mirdan/standards/frameworks/langchain.yaml
mirdan/standards/frameworks/langgraph.yaml
mirdan/standards/frameworks/micronaut.yaml
mirdan/standards/frameworks/milvus.yaml
mirdan/standards/frameworks/neo4j.yaml
mirdan/standards/frameworks/nestjs.yaml
mirdan/standards/frameworks/nextjs.yaml
mirdan/standards/frameworks/nuxt.yaml
mirdan/standards/frameworks/pinecone.yaml
mirdan/standards/frameworks/qdrant.yaml
mirdan/standards/frameworks/quarkus.yaml
mirdan/standards/frameworks/react.yaml
mirdan/standards/frameworks/springboot.yaml
mirdan/standards/frameworks/sveltekit.yaml
mirdan/standards/frameworks/tailwind.yaml
mirdan/standards/frameworks/vue.yaml
mirdan/standards/frameworks/weaviate.yaml
mirdan/standards/languages/go.yaml
mirdan/standards/languages/java.yaml
mirdan/standards/languages/javascript.yaml
mirdan/standards/languages/python.yaml
mirdan-0.0.6.dist-info/METADATA
mirdan-0.0.6.dist-info/WHEEL
mirdan-0.0.6.dist-info/entry_points.txt
mirdan-0.0.6.dist-info/RECORD
