Metadata-Version: 2.4
Name: mirdan
Version: 0.0.6
Summary: AI Code Quality Orchestrator - Automatically transforms developer prompts into high-quality, structured requests
Author: Sean Corkum
License-Expression: MIT
Keywords: ai,code-quality,llm,mcp,prompt-engineering
Classifier: Development Status :: 3 - Alpha
Classifier: Intended Audience :: Developers
Classifier: License :: OSI Approved :: MIT License
Classifier: Programming Language :: Python :: 3.11
Classifier: Programming Language :: Python :: 3.12
Classifier: Programming Language :: Python :: 3.13
Classifier: Topic :: Software Development :: Quality Assurance
Requires-Python: >=3.11
Requires-Dist: fastmcp>=2.0.0
Requires-Dist: jinja2>=3.1.0
Requires-Dist: pydantic>=2.0
Requires-Dist: pyyaml>=6.0
Provides-Extra: dev
Requires-Dist: mypy>=1.13; extra == 'dev'
Requires-Dist: pytest-asyncio>=0.24; extra == 'dev'
Requires-Dist: pytest>=8.0; extra == 'dev'
Requires-Dist: ruff>=0.8; extra == 'dev'
Requires-Dist: types-pyyaml>=6.0; extra == 'dev'
